{"id":"b98d07be-d888-45c7-85d8-806b5dd352a6","map":"AmbroseValley","date":"2026-02-13","duration_ms":347000,"stats":{"humans":1,"bots":0,"combat_events":12,"loot_events":39,"storm_deaths":0},"players":[{"id":"c830d8d5-e7c2-4d09-935e-d3c79c5903a1","is_bot":false,"color":"#00FF88","path":[{"t":0,"px":61.9,"py":488.6},{"t":30000,"px":78.1,"py":476.4},{"t":35000,"px":105.9,"py":454.6},{"t":40000,"px":104.9,"py":444.8},{"t":45000,"px":96.8,"py":421.5},{"t":50000,"px":88.9,"py":418.6},{"t":55000,"px":94.2,"py":409.4},{"t":60000,"px":103.1,"py":401.4},{"t":66000,"px":124.4,"py":396.7},{"t":71000,"px":160.6,"py":405.6},{"t":76000,"px":192.2,"py":414.4},{"t":81000,"px":221.6,"py":415.7},{"t":86000,"px":249.5,"py":418.7},{"t":91000,"px":284.4,"py":415.4},{"t":96000,"px":303.1,"py":405.2},{"t":101000,"px":329.1,"py":399.8},{"t":106000,"px":318.7,"py":401.6},{"t":111000,"px":325.1,"py":400.0},{"t":116000,"px":344.6,"py":387.0},{"t":121000,"px":349.8,"py":388.6},{"t":126000,"px":354.3,"py":392.9},{"t":136000,"px":360.9,"py":395.3},{"t":141000,"px":373.7,"py":411.8},{"t":146000,"px":378.4,"py":407.4},{"t":151000,"px":388.2,"py":390.6},{"t":156000,"px":416.0,"py":377.0},{"t":161000,"px":429.1,"py":359.9},{"t":166000,"px":438.2,"py":381.1},{"t":171000,"px":437.3,"py":386.4},{"t":176000,"px":446.8,"py":380.2},{"t":181000,"px":465.0,"py":379.8},{"t":186000,"px":459.3,"py":379.2},{"t":191000,"px":471.4,"py":383.0},{"t":196000,"px":484.7,"py":394.7},{"t":201000,"px":492.7,"py":423.4},{"t":206000,"px":508.5,"py":451.7},{"t":211000,"px":518.2,"py":479.9},{"t":216000,"px":511.4,"py":488.2},{"t":221000,"px":490.1,"py":497.2},{"t":226000,"px":466.9,"py":508.0},{"t":231000,"px":448.9,"py":516.8},{"t":236000,"px":429.2,"py":525.0},{"t":242000,"px":422.2,"py":506.0},{"t":252000,"px":426.4,"py":495.2},{"t":257000,"px":441.8,"py":491.9},{"t":262000,"px":411.2,"py":488.4},{"t":267000,"px":387.7,"py":505.6},{"t":272000,"px":386.6,"py":517.9},{"t":277000,"px":386.4,"py":534.1},{"t":282000,"px":411.5,"py":542.6},{"t":287000,"px":440.4,"py":554.9},{"t":292000,"px":473.7,"py":562.1},{"t":297000,"px":482.9,"py":559.4},{"t":302000,"px":479.9,"py":563.4},{"t":307000,"px":477.1,"py":564.3},{"t":312000,"px":494.9,"py":555.9},{"t":317000,"px":511.6,"py":549.2},{"t":322000,"px":515.9,"py":532.1},{"t":327000,"px":528.3,"py":533.9},{"t":332000,"px":562.4,"py":532.5},{"t":337000,"px":598.8,"py":538.5},{"t":342000,"px":630.4,"py":550.8},{"t":347000,"px":644.5,"py":563.4}],"events":[{"t":50000,"type":"Loot","px":88.9,"py":418.6},{"t":51000,"type":"Loot","px":86.5,"py":417.6},{"t":53000,"type":"Loot","px":87.9,"py":414.5},{"t":58000,"type":"Loot","px":106.4,"py":404.8},{"t":104000,"type":"BotKill","px":320.1,"py":398.8},{"t":108000,"type":"Loot","px":316.7,"py":410.5},{"t":108000,"type":"Loot","px":316.7,"py":410.5},{"t":114000,"type":"Loot","px":343.2,"py":389.9},{"t":119000,"type":"Loot","px":352.1,"py":386.9},{"t":130000,"type":"BotKill","px":355.2,"py":392.7},{"t":136000,"type":"BotKill","px":360.9,"py":395.3},{"t":142000,"type":"Loot","px":376.0,"py":415.5},{"t":142000,"type":"Loot","px":376.0,"py":415.5},{"t":143000,"type":"Loot","px":376.0,"py":415.5},{"t":143000,"type":"Loot","px":376.0,"py":415.5},{"t":143000,"type":"Loot","px":376.0,"py":415.5},{"t":144000,"type":"Loot","px":376.0,"py":415.5},{"t":144000,"type":"Loot","px":376.0,"py":415.5},{"t":150000,"type":"Loot","px":387.5,"py":390.7},{"t":151000,"type":"Loot","px":387.5,"py":390.7},{"t":168000,"type":"BotKill","px":438.1,"py":382.6},{"t":171000,"type":"BotKill","px":437.3,"py":386.4},{"t":174000,"type":"Loot","px":434.3,"py":384.1},{"t":174000,"type":"Loot","px":434.3,"py":384.1},{"t":177000,"type":"Loot","px":447.3,"py":379.0},{"t":177000,"type":"Loot","px":447.3,"py":379.0},{"t":187000,"type":"BotKill","px":459.3,"py":379.2},{"t":196000,"type":"Loot","px":484.7,"py":394.7},{"t":197000,"type":"Loot","px":484.7,"py":394.7},{"t":227000,"type":"Loot","px":462.5,"py":509.4},{"t":228000,"type":"Loot","px":462.5,"py":509.4},{"t":231000,"type":"BotKill","px":450.7,"py":516.0},{"t":236000,"type":"Loot","px":429.2,"py":525.0},{"t":236000,"type":"Loot","px":429.2,"py":525.0},{"t":242000,"type":"Loot","px":422.0,"py":505.8},{"t":249000,"type":"BotKill","px":425.8,"py":504.5},{"t":256000,"type":"Loot","px":441.9,"py":491.0},{"t":268000,"type":"Loot","px":387.7,"py":505.6},{"t":268000,"type":"Loot","px":387.7,"py":505.6},{"t":269000,"type":"Loot","px":387.7,"py":505.6},{"t":296000,"type":"BotKill","px":483.3,"py":559.0},{"t":301000,"type":"BotKill","px":479.9,"py":563.4},{"t":306000,"type":"BotKill","px":477.1,"py":564.3},{"t":307000,"type":"BotKill","px":477.1,"py":564.3},{"t":314000,"type":"Loot","px":504.0,"py":552.4},{"t":314000,"type":"Loot","px":504.0,"py":552.4},{"t":316000,"type":"Loot","px":511.8,"py":550.5},{"t":316000,"type":"Loot","px":511.8,"py":550.5},{"t":320000,"type":"Loot","px":513.6,"py":540.5},{"t":320000,"type":"Loot","px":513.6,"py":540.5},{"t":323000,"type":"Loot","px":515.9,"py":532.1}]}]}